verilator-tutorial/demo/demo.v
module demo #(
    parameter WORDSIZE = 8
)(
    input  signed [WORDSIZE-1:0] iData0,   
    input  signed [WORDSIZE-1:0] iData1,
    input  signed [WORDSIZE-1:0] iData2,
    input                         iClk,
    input                         iRstN,

    output reg signed [WORDSIZE-1:0] sum
);  
    // buffer0(b0) is used to match iData0 to output(b1) of the comparison of iData1 and iData2
    reg [WORDSIZE-1:0] b0, b1;

    always @(posedge iClk or negedge iRstN) begin
        if (!iRstN) begin
            b0 <= 0;
            b1 <= 0;
            sum <= 0;
        end else begin
            sum <= b0 + b1;
            b0 <= iData0;
            if (iData1 < iData2) begin
                b1 <= iData1;
            end else begin
                b1 <= iData2;
            end
        end
    end
endmodule

verilator-tutorial/demo/demoWaveform.vcd
$version Generated by VerilatedVcd $end
$date Mon Mar  3 08:39:58 2025 $end
$timescale 1ps $end

 $scope module TOP $end
  $var wire  1 & iClk $end
  $var wire 16 # iData0 [15:0] $end
  $var wire 16 $ iData1 [15:0] $end
  $var wire 16 % iData2 [15:0] $end
  $var wire  1 ' iRstN $end
  $var wire 16 ( sum [15:0] $end
  $scope module demo $end
   $var wire 16 ) b0 [15:0] $end
   $var wire 16 * b1 [15:0] $end
   $var wire  1 & iClk $end
   $var wire 16 # iData0 [15:0] $end
   $var wire 16 $ iData1 [15:0] $end
   $var wire 16 % iData2 [15:0] $end
   $var wire  1 ' iRstN $end
   $var wire 16 ( sum [15:0] $end
  $upscope $end
 $upscope $end
$enddefinitions $end


#0
b0000000000000000 #
b0000000000000000 $
b0000000000000000 %
1&
0'
b0000000000000000 (
b0000000000000000 )
b0000000000000000 *
#1
0&
#2
1&
#3
0&
#4
1&
1'
#5
0&
#6
b0011100000111100 #
b1101110011000010 $
b0000010110100110 %
1&
b0011100000111100 )
b1101110011000010 *
#7
0&
#8
b1101010100111111 #
b1110111111110001 $
b0010010101010110 %
1&
b0001010011111110 (
b1101010100111111 )
b1110111111110001 *
#9
0&
#10
b0000100010100110 #
b0010110001111001 $
b0000101110110101 %
1&
b1100010100110000 (
b0000100010100110 )
b0000101110110101 *
#11
0&
#12
b0000011001011000 #
b1100001011010101 $
b0000010000010000 %
1&
b0001010001011011 (
b0000011001011000 )
b1100001011010101 *
#13
0&
#14
b0000110010001111 #
b1111001100110111 $
b1111100111111001 %
1&
b1100100100101101 (
b0000110010001111 )
b1111001100110111 *
#15
0&
#16
b0001111111101111 #
b1111010101100101 $
b0011010000000100 %
1&
b1111111111000110 (
b0001111111101111 )
b1111010101100101 *
#17
0&
#18
b0011000100001111 #
b0011011011101111 $
b1101100100111100 %
1&
b0001010101010100 (
b0011000100001111 )
b1101100100111100 *
#19
0&
#20
b1101010110111000 #
b1110101110001111 $
b1110000001100110 %
1&
b0000101001001011 (
b1101010110111000 )
b1110000001100110 *
#21
0&
#22
b0010011000100100 #
b1101111101001111 $
b0001100010100011 %
1&
b1011011000011110 (
b0010011000100100 )
b1101111101001111 *
#23
0&
#24
b1110000111000101 #
b0001001000000011 $
b1110101101001101 %
1&
b0000010101110011 (
b1110000111000101 )
b1110101101001101 *
#25
0&
#26
b1110101000001010 #
b1111010111000010 $
b0000010111000101 %
1&
b1100110100010010 (
b1110101000001010 )
b1111010111000010 *
#27
0&
#28
b0000011110100101 #
b1101110111110000 $
b0001100110100101 %
1&
b1101111111001100 (
b0000011110100101 )
b1101110111110000 *
#29
0&
#30
b0001000111101000 #
b0000001011000100 $
b1111000101011110 %
1&
b1110010110010101 (
b0001000111101000 )
b1111000101011110 *
#31
0&
#32
b1100001110101001 #
b1101001001011111 $
b0001111101111110 %
1&
b0000001101000110 (
b1100001110101001 )
b1101001001011111 *
#33
0&
#34
b1111101111010011 #
b1100101100111111 $
b1101100001001110 %
1&
b1001011000001000 (
b1111101111010011 )
b1100101100111111 *
#35
0&
#36
b0011101111010101 #
b0000111001100110 $
b1100100111101011 %
1&
b1100011100010010 (
b0011101111010101 )
b1100100111101011 *
#37
0&
#38
b0011101011111101 #
b0001100010110110 $
b0010101000011001 %
1&
b0000010111000000 (
b0011101011111101 )
b0001100010110110 *
#39
0&
#40
b0010111010010100 #
b0011100000101101 $
b1101011000111010 %
1&
b0101001110110011 (
b0010111010010100 )
b1101011000111010 *
#41
0&
#42
b1101110100001010 #
b0001101000100100 $
b0000110111001111 %
1&
b0000010011001110 (
b1101110100001010 )
b0000110111001111 *
#43
0&
#44
b0000010010100100 #
b0000110001000000 $
b0011010001101110 %
1&
b1110101011011001 (
b0000010010100100 )
b0000110001000000 *
#45
0&
#46
b1111010111010111 #
b1110011001000101 $
b0001000101101000 %
1&
b0001000011100100 (
b1111010111010111 )
b1110011001000101 *
#47
0&
#48
b0010010110100110 #
b1111010101111111 $
b0010110110000111 %
1&
b1101110000011100 (
b0010010110100110 )
b1111010101111111 *
#49
0&
#50
b1100001001110010 #
b0000110101110101 $
b1101111010011101 %
1&
b0001101100100101 (
b1100001001110010 )
b1101111010011101 *
#51
0&
#52
b0000001011000001 #
b0001111000110110 $
b1100110010101100 %
1&
b1010000100001111 (
b0000001011000001 )
b1100110010101100 *
#53
0&
#54
b1111000110000101 #
b1100110000110010 $
b1101100001101100 %
1&
b1100111101101101 (
b1111000110000101 )
b1100110000110010 *
#55
0&
#56
b1101101101011010 #
b0011111000000101 $
b0010100110110101 %
1&
b1011110110110111 (
b1101101101011010 )
b0010100110110101 *
#57
0&
#58
b1111110100110101 #
b0001101000110111 $
b1101111100001001 %
1&
b0000010100001111 (
b1111110100110101 )
b1101111100001001 *
#59
0&
#60
b0000011010100101 #
b1111101011101100 $
b0001001101001010 %
1&
b1101110000111110 (
b0000011010100101 )
b1111101011101100 *
#61
0&
#62
b1101000101001001 #
b1111000001011100 $
b1110110001010010 %
1&
b0000000110010001 (
b1101000101001001 )
b1110110001010010 *
#63
0&
#64
b1100011101011010 #
b1100110110101011 $
b1110101000011010 %
1&
b1011110110011011 (
b1100011101011010 )
b1100110110101011 *
#65
0&
#66
b0001001100100101 #
b0011001011010000 $
b1101010000010110 %
1&
b1001010100000101 (
b0001001100100101 )
b1101010000010110 *
#67
0&
#68
b1100110100111001 #
b1100010100101001 $
b1101010100110010 %
1&
b1110011100111011 (
b1100110100111001 )
b1100010100101001 *
#69
0&
#70
b0010010000100100 #
b0010110101110010 $
b1111011010011101 %
1&
b1001001001100010 (
b0010010000100100 )
b1111011010011101 *
#71
0&
#72
b0000011000100111 #
b1100101010110010 $
b1101000011101001 %
1&
b0001101011000001 (
b0000011000100111 )
b1100101010110010 *
#73
0&
#74
b1100110110100111 #
b1111000101110101 $
b0010101101100101 %
1&
b1101000011011001 (
b1100110110100111 )
b1111000101110101 *
#75
0&
#76
b0011001101000000 #
b0001111000100110 $
b0001111100000001 %
1&
b1011111100011100 (
b0011001101000000 )
b0001111000100110 *
#77
0&
#78
b1101001101011110 #
b0001001010001001 $
b0011000010111101 %
1&
b0101000101100110 (
b1101001101011110 )
b0001001010001001 *
#79
0&
#80
b0010011101100111 #
b0001101110001011 $
b0011100101110111 %
1&
b1110010111100111 (
b0010011101100111 )
b0001101110001011 *
#81
0&
#82
b1111010111010110 #
b0001100111100011 $
b1110001100011011 %
1&
b0100001011110010 (
b1111010111010110 )
b1110001100011011 *
#83
0&
#84
b1101001111011011 #
b0001110001010100 $
b0011100111011111 %
1&
b1101100011110001 (
b1101001111011011 )
b0001110001010100 *
#85
0&
#86
b1100010011011110 #
b0000110000010001 $
b0010101110101001 %
1&
b1111000000101111 (
b1100010011011110 )
b0000110000010001 *
#87
0&
#88
b1101101010101111 #
b1101101001111000 $
b1101101110101001 %
1&
b1101000011101111 (
b1101101010101111 )
b1101101001111000 *
#89
0&
#90
b1111100100110000 #
b1111110110000010 $
b1101010111100110 %
1&
b1011010100100111 (
b1111100100110000 )
b1101010111100110 *
#91
0&
#92
b0011011001010010 #
b0011011110001010 $
b0001100101110000 %
1&
b1100111100010110 (
b0011011001010010 )
b0001100101110000 *
#93
0&
#94
b0000000111011110 #
b1111010010110010 $
b0001110001110110 %
1&
b0100111111000010 (
b0000000111011110 )
b1111010010110010 *
#95
0&
#96
b1111111111011001 #
b1100110011111001 $
b0011100101101100 %
1&
b1111011010010000 (
b1111111111011001 )
b1100110011111001 *
#97
0&
#98
b1101001001100010 #
b0001100001101111 $
b0000110111001010 %
1&
b1100110011010010 (
b1101001001100010 )
b0000110111001010 *
#99
0&
#100
b1100000101010101 #
b0001111110110011 $
b0001000000011111 %
1&
b1110000000101100 (
b1100000101010101 )
b0001000000011111 *
#101
0&
#102
b0011110000110011 #
b0001010100010010 $
b0010101111100111 %
1&
b1101000101110100 (
b0011110000110011 )
b0001010100010010 *
#103
0&
#104
b0010110011001010 #
b1100000110111011 $
b1101000010101000 %
1&
b0101000101000101 (
b0010110011001010 )
b1100000110111011 *
#105
0&
#106
b0011010000100011 #
b1100011111110101 $
b1111001010111011 %
1&
b1110111010000101 (
b0011010000100011 )
b1100011111110101 *
#107
0&
#108
b0011010111010100 #
b1100110110001111 $
b1101010001000000 %
1&
b1111110000011000 (
b0011010111010100 )
b1100110110001111 *
#109
0&
#110
b0000110000101001 #
b0001100101110011 $
b0001101110111011 %
1&
b0000001101100011 (
b0000110000101001 )
b0001100101110011 *
#111
0&
#112
b0000100000100101 #
b0001001111010111 $
b1111111010110100 %
1&
b0010010110011100 (
b0000100000100101 )
b1111111010110100 *
#113
0&
#114
b0011000110000101 #
b1110100111111011 $
b0010100100000000 %
1&
b0000011011011001 (
b0011000110000101 )
b1110100111111011 *
#115
0&
#116
b0011000010110100 #
b1100110011111000 $
b1110111001001100 %
1&
b0001101110000000 (
b0011000010110100 )
b1100110011111000 *
#117
0&
#118
b0000110010100100 #
b0010100110100101 $
b0000110011000100 %
1&
b1111110110101100 (
b0000110010100100 )
b0000110011000100 *
#119
0&
#120
b0001010100000101 #
b1100111110101100 $
b0000011111101111 %
1&
b0001100101101000 (
b0001010100000101 )
b1100111110101100 *
#121
0&
#122
b1101100001001001 #
b0000000101000110 $
b1111110111110010 %
1&
b1110010010110001 (
b1101100001001001 )
b1111110111110010 *
#123
0&
#124
b1111111101011111 #
b0011001101111001 $
b0001101110000100 %
1&
b1101011000111011 (
b1111111101011111 )
b0001101110000100 *
#125
0&
#126
b1101101001101101 #
b0010000101010001 $
b1100011110101111 %
1&
b0001101011100011 (
b1101101001101101 )
b1100011110101111 *
#127
0&
#128
b0001111100101111 #
b0010010011100010 $
b1110010001110111 %
1&
b1010001000011100 (
b0001111100101111 )
b1110010001110111 *
#129
0&
#130
b0010101000000011 #
b0010000010111001 $
b0011000100100010 %
1&
b0000001110100110 (
b0010101000000011 )
b0010000010111001 *
#131
0&
#132
b0010110010110101 #
b0000000000010001 $
b1100011001101001 %
1&
b0100101010111100 (
b0010110010110101 )
b1100011001101001 *
#133
0&
#134
b1111000111101111 #
b0000000110101000 $
b0010100100101100 %
1&
b1111001100011110 (
b1111000111101111 )
b0000000110101000 *
#135
0&
#136
b1111011001011101 #
b1100000111000110 $
b0010000101110011 %
1&
b1111001110010111 (
b1111011001011101 )
b1100000111000110 *
#137
0&
#138
b1110100011010100 #
b1111011001111001 $
b1100010111100011 %
1&
b1011100000100011 (
b1110100011010100 )
b1100010111100011 *
#139
0&
#140
b0011100000111101 #
b0000001100101111 $
b1111101110001101 %
1&
b1010111010110111 (
b0011100000111101 )
b1111101110001101 *
#141
0&
#142
b0011100010001011 #
b0001001101111101 $
b1110001101001001 %
1&
b0011001111001010 (
b0011100010001011 )
b1110001101001001 *
#143
0&
#144
b1100011111001100 #
b0000001101010011 $
b0000001010101100 %
1&
b0001101111010100 (
b1100011111001100 )
b0000001010101100 *
#145
0&
#146
b1100010011111101 #
b0010001101011110 $
b1100011100001000 %
1&
b1100101001111000 (
b1100010011111101 )
b1100011100001000 *
#147
0&
#148
b0011011011111100 #
b1100011111101000 $
b0001011000111010 %
1&
b1000110000000101 (
b0011011011111100 )
b1100011111101000 *
#149
0&
#150
b0000101110101111 #
b1101111110000110 $
b0010111100010111 %
1&
b1111111011100100 (
b0000101110101111 )
b1101111110000110 *
#151
0&
#152
b1101100011000001 #
b1101000110000111 $
b1110101010000110 %
1&
b1110101100110101 (
b1101100011000001 )
b1101000110000111 *
#153
0&
#154
b1110110010110000 #
b0001000001101101 $
b0011111000111001 %
1&
b1010101001001000 (
b1110110010110000 )
b0001000001101101 *
#155
0&
#156
b1110001011011100 #
b1100011010111110 $
b1101101010001001 %
1&
b1111110100011101 (
b1110001011011100 )
b1100011010111110 *
#157
0&
#158
b1101000010000011 #
b0001000000100010 $
b1111111010101100 %
1&
b1010100110011010 (
b1101000010000011 )
b1111111010101100 *
#159
0&
#160
b0001100110110100 #
b1101111001100010 $
b1101110010101110 %
1&
b1100111100101111 (
b0001100110110100 )
b1101110010101110 *
#161
0&
#162
b0000001001101111 #
b1100001010010011 $
b0000010011001110 %
1&
b1111011001100010 (
b0000001001101111 )
b1100001010010011 *
#163
0&
#164
b1100010000111011 #
b1101010110111001 $
b1100011000110000 %
1&
b1100010100000010 (
b1100010000111011 )
b1100011000110000 *
#165
0&
#166
b1101101101011011 #
b0011001100111100 $
b1111001111001110 %
1&
b1000101001101011 (
b1101101101011011 )
b1111001111001110 *
#167
0&
#168
b1100101000011010 #
b1100100000100000 $
b0001011000100111 %
1&
b1100111100101001 (
b1100101000011010 )
b1100100000100000 *
#169
0&
#170
b0010111110001101 #
b0011010100110100 $
b1101101111000011 %
1&
b1001001000111010 (
b0010111110001101 )
b1101101111000011 *
#171
0&
#172
b1101101100000010 #
b1100111101011111 $
b1100000011011111 %
1&
b0000101101010000 (
b1101101100000010 )
b1100000011011111 *
#173
0&
#174
b1110111101011110 #
b1101101010000010 $
b1111100000100111 %
1&
b1001101111100001 (
b1110111101011110 )
b1101101010000010 *
#175
0&
#176
b0011011011001110 #
b1111101111101010 $
b0011111011001100 %
1&
b1100100111100000 (
b0011011011001110 )
b1111101111101010 *
#177
0&
#178
b0010101000110000 #
b0000101101010101 $
b1100010101010011 %
1&
b0011001010111000 (
b0010101000110000 )
b1100010101010011 *
#179
0&
#180
b0001110101001001 #
b0001100100011111 $
b0001000111000011 %
1&
b1110111110000011 (
b0001110101001001 )
b0001000111000011 *
#181
0&
#182
b1110001010010100 #
b0010101110011000 $
b1111011110000100 %
1&
b0010111100001100 (
b1110001010010100 )
b1111011110000100 *
#183
0&
#184
b1111101010110111 #
b1101011001011001 $
b0010110000000000 %
1&
b1101101000011000 (
b1111101010110111 )
b1101011001011001 *
#185
0&
#186
b0001101001011011 #
b0010100110000011 $
b0001110010100111 %
1&
b1101000100010000 (
b0001101001011011 )
b0001110010100111 *
#187
0&
#188
b1111101101011111 #
b1101110101111000 $
b1101001000100010 %
1&
b0011011100000010 (
b1111101101011111 )
b1101001000100010 *
#189
0&
#190
b0010110100111110 #
b0000101110100000 $
b0010000100000001 %
1&
b1100110110000001 (
b0010110100111110 )
b0000101110100000 *
#191
0&
#192
b0001111111111100 #
b1101001110100011 $
b1100011110001111 %
1&
b0011100011011110 (
b0001111111111100 )
b1100011110001111 *
#193
0&
#194
b1111100111000110 #
b0000110011111110 $
b1110110100000001 %
1&
b1110011110001011 (
b1111100111000110 )
b1110110100000001 *
#195
0&
#196
b0011110000000011 #
b1101101001011111 $
b1110000101110010 %
1&
b1110011011000111 (
b0011110000000011 )
b1101101001011111 *
#197
0&
#198
b1110111011011010 #
b0001000101110111 $
b0000010000101100 %
1&
b0001011001100010 (
b1110111011011010 )
b0000010000101100 *
#199
0&
#200
b1101010110001001 #
b1111111000101100 $
b0011101111111110 %
1&
b1111001100000110 (
b1101010110001001 )
b1111111000101100 *
#201
0&
#202
b1111001100011010 #
b0001110111001100 $
b0010111111010110 %
1&
b1101001110110101 (
b1111001100011010 )
b0001110111001100 *
#203
0&
#204
b1111110110010001 #
b0001011110111110 $
b0000111011100011 %
1&
b0001000011100110 (
b1111110110010001 )
b0000111011100011 *
#205
0&
#206
b0010100111111010 #
b1100010010101001 $
b0001001100110000 %
1&
b0000110001110100 (
b0010100111111010 )
b1100010010101001 *
#207
0&
#208
b0011000101000010 #
b1101000111110001 $
b0001010110000011 %
1&
b1110111010100011 (
b0011000101000010 )
b1101000111110001 *
#209
0&
#210
b0010000001010000 #
b0011111000101100 $
b0010101000000110 %
1&
b0000001100110011 (
b0010000001010000 )
b0010101000000110 *
#211
0&
#212
b1101000000101101 #
b0001011001101011 $
b1100100111001111 %
1&
b0100101001010110 (
b1101000000101101 )
b1100100111001111 *
#213
0&
#214
b1111001101110010 #
b0011110000011011 $
b1110101110000011 %
1&
b1001100111111100 (
b1111001101110010 )
b1110101110000011 *
#215
0&
#216
b1100000000100101 #
b0000010111100000 $
b0010000010111111 %
1&
b1101111011110101 (
b1100000000100101 )
b0000010111100000 *
#217
0&
#218
b0011111110011111 #
b1100101010000101 $
b0011100001111001 %
1&
b1100011000000101 (
b0011111110011111 )
b1100101010000101 *
#219
0&
#220
b1110110111011010 #
b1100100110001100 $
b1110100010010101 %
1&
b0000101000100100 (
b1110110111011010 )
b1100100110001100 *
#221
0&
#222
b1110001101011001 #
b0011010010010001 $
b1101101111010110 %
1&
b1011011101100110 (
b1110001101011001 )
b1101101111010110 *
#223
0&
#224
b0010101100000111 #
b1101010001010101 $
b1111000111011010 %
1&
b1011111100101111 (
b0010101100000111 )
b1101010001010101 *
#225
0&
#226
b1110001011011100 #
b1100100010110110 $
b0000011000010110 %
1&
b1111111101011100 (
b1110001011011100 )
b1100100010110110 *
#227
0&
#228
b1101000110100101 #
b1111010100011011 $
b0010110000011000 %
1&
b1010101110010010 (
b1101000110100101 )
b1111010100011011 *
#229
0&
#230
b0001111001001011 #
b0001000100000110 $
b0000000111010111 %
1&
b1100011011000000 (
b0001111001001011 )
b0000000111010111 *
#231
0&
#232
b0001010000011110 #
b0010000011100100 $
b0001111000101001 %
1&
b0010000000100010 (
b0001010000011110 )
b0001111000101001 *
#233
0&
#234
b1101010101011010 #
b1101011111000011 $
b0011100101010111 %
1&
b0011001001000111 (
b1101010101011010 )
b1101011111000011 *
#235
0&
#236
b1101101100101111 #
b1101110110100000 $
b0000010101100100 %
1&
b1010110100011101 (
b1101101100101111 )
b1101110110100000 *
#237
0&
#238
b1101100101011101 #
b1100101111000001 $
b0011100111000001 %
1&
b1011100011001111 (
b1101100101011101 )
b1100101111000001 *
#239
0&
#240
b0010100000101111 #
b0001111001011111 $
b0011101111001000 %
1&
b1010010100011110 (
b0010100000101111 )
b0001111001011111 *
#241
0&
#242
b0000101101001101 #
b0011111011110101 $
b0011001010001101 %
1&
b0100011010001110 (
b0000101101001101 )
b0011001010001101 *
#243
0&
#244
b0011111010011011 #
b0000000010000001 $
b1111101100010000 %
1&
b0011110111011010 (
b0011111010011011 )
b1111101100010000 *
#245
0&
#246
b1100100010000011 #
b1110101101001010 $
b0011100101001001 %
1&
b0011100110101011 (
b1100100010000011 )
b1110101101001010 *
#247
0&
#248
b1110010011000101 #
b0010011110001000 $
b0001101001101100 %
1&
b1011001111001101 (
b1110010011000101 )
b0001101001101100 *
#249
0&
#250
b1111000010111111 #
b1101100101100101 $
b1101110101001110 %
1&
b1111111100110001 (
b1111000010111111 )
b1101100101100101 *
#251
0&
#252
b0001010101110010 #
b1110111011010000 $
b0000111100011110 %
1&
b1100101000100100 (
b0001010101110010 )
b1110111011010000 *
#253
0&
#254
b1101011111111111 #
b1111110101100100 $
b1111011110100001 %
1&
b0000010001000010 (
b1101011111111111 )
b1111011110100001 *
#255
0&
#256
b1110010011101010 #
b0000101000101001 $
b1110000010010001 %
1&
b1100111110100000 (
b1110010011101010 )
b1110000010010001 *
#257
0&
#258
b1100001110101010 #
b0010101010010011 $
b1110000001111000 %
1&
b1100010101111011 (
b1100001110101010 )
b1110000001111000 *
#259
0&
#260
b1101111111100101 #
b0010110110010010 $
b0001111110011000 %
1&
b1010010000100010 (
b1101111111100101 )
b0001111110011000 *
#261
0&
#262
b0001010101011110 #
b0001111111111010 $
b1100101000100011 %
1&
b1111111101111101 (
b0001010101011110 )
b1100101000100011 *
#263
0&
#264
b0011110001011010 #
b0000110010011010 $
b1100010010100110 %
1&
b1101111110000001 (
b0011110001011010 )
b1100010010100110 *
#265
0&
#266
b0011010101100110 #
b0011100011101100 $
b1101001001110111 %
1&
b0000000100000000 (
b0011010101100110 )
b1101001001110111 *
#267
0&
#268
b1110111010000101 #
b1101101111001011 $
b1110011000011011 %
1&
b0000011111011101 (
b1110111010000101 )
b1101101111001011 *
#269
0&
#270
b1110101101010011 #
b1101100011000101 $
b1101010110000100 %
1&
b1100101001010000 (
b1110101101010011 )
b1101010110000100 *
#271
0&
#272
b0010011101110100 #
b0000100110111010 $
b1110000110011000 %
1&
b1100000011010111 (
b0010011101110100 )
b1110000110011000 *
#273
0&
#274
b0011011111010100 #
b0010111111100100 $
b1110110101001000 %
1&
b0000100100001100 (
b0011011111010100 )
b1110110101001000 *
#275
0&
#276
b1110000000111100 #
b1101101010100000 $
b0001111000000110 %
1&
b0010010100011100 (
b1110000000111100 )
b1101101010100000 *
#277
0&
#278
b1101111111111001 #
b0010000010001001 $
b1110110011000110 %
1&
b1011101011011100 (
b1101111111111001 )
b1110110011000110 *
#279
0&
#280
b0000101011110101 #
b1101101000000110 $
b0011111100001001 %
1&
b1100110010111111 (
b0000101011110101 )
b1101101000000110 *
#281
0&
#282
b1110000001010101 #
b0011010011001110 $
b1111111111111100 %
1&
b1110010011111011 (
b1110000001010101 )
b1111111111111100 *
#283
0&
#284
b1110110001100110 #
b0001011011100001 $
b1110001100111010 %
1&
b1110000001010001 (
b1110110001100110 )
b1110001100111010 *
#285
0&
#286
b1101010000010111 #
b0000010100110100 $
b1110111110011011 %
1&
b1100111110100000 (
b1101010000010111 )
b1110111110011011 *
#287
0&
#288
b1111001000001100 #
b1101001101101100 $
b0011000110110011 %
1&
b1100001110110010 (
b1111001000001100 )
b1101001101101100 *
#289
0&
#290
b0010111011011001 #
b1111001101011011 $
b1100010110100000 %
1&
b1100010101111000 (
b0010111011011001 )
b1100010110100000 *
#291
0&
#292
b1101101110001110 #
b0001111101110011 $
b1111110111000010 %
1&
b1111010001111001 (
b1101101110001110 )
b1111110111000010 *
#293
0&
#294
b0010100110110110 #
b1101111100111001 $
b0001000000000010 %
1&
b1101100101010000 (
b0010100110110110 )
b1101111100111001 *
#295
0&
#296
b1101011011010101 #
b0010011000101000 $
b1111110001110111 %
1&
b0000100011101111 (
b1101011011010101 )
b1111110001110111 *
#297
0&
#298
b1100011100011000 #
b1100100110000101 $
b0010111000000010 %
1&
b1101001101001100 (
b1100011100011000 )
b1100100110000101 *
#299
0&
#300
b1100100001011000 #
b1110001111001111 $
b0001101111001000 %
1&
b1001000010011101 (
b1100100001011000 )
b1110001111001111 *
#301
0&
#302
b1100100001100101 #
b0011101100000001 $
b0000000000101110 %
1&
b1010110000100111 (
b1100100001100101 )
b0000000000101110 *
#303
0&
#304
b0011100110100001 #
b1100001111001011 $
b0001000110110101 %
1&
b1100100010010011 (
b0011100110100001 )
b1100001111001011 *
#305
0&
#306
b1110111110001110 #
b0011011111011110 $
b0010101010101000 %
1&
b1111110101101100 (
b1110111110001110 )
b0010101010101000 *
#307
0&
#308
b1100101101110000 #
b0010000111000100 $
b0001111000111101 %
1&
b0001101000110110 (
b1100101101110000 )
b0001111000111101 *
#309
0&
#310
b0011001100100111 #
b0010001000111111 $
b1101001101110000 %
1&
b1110100110101101 (
b0011001100100111 )
b1101001101110000 *
#311
0&
#312
b0010111100010110 #
b0001000111011011 $
b0011100011101001 %
1&
b0000011010010111 (
b0010111100010110 )
b0001000111011011 *
#313
0&
#314
b0001000011110001 #
b0010000110001001 $
b0001000000001101 %
1&
b0100000011110001 (
b0001000011110001 )
b0001000000001101 *
#315
0&
#316
b0010011100111110 #
b0010101001010111 $
b1111100000101111 %
1&
b0010000011111110 (
b0010011100111110 )
b1111100000101111 *
#317
0&
#318
b1100010101100011 #
b1100010110001101 $
b1111010101100000 %
1&
b0001111101101101 (
b1100010101100011 )
b1100010110001101 *
#319
0&
#320
b1110110101010100 #
b0000111110001000 $
b1111111111111111 %
1&
b1000101011110000 (
b1110110101010100 )
b1111111111111111 *
#321
0&
#322
b0001000110010001 #
b0000100111011001 $
b1111011111001011 %
1&
b1110110101010011 (
b0001000110010001 )
b1111011111001011 *
#323
0&
#324
b0001110001011010 #
b0011100001100110 $
b0000111000110001 %
1&
b0000100101011100 (
b0001110001011010 )
b0000111000110001 *
#325
0&
#326
b0001110110010000 #
b0011011110111001 $
b0010110000110011 %
1&
b0010101010001011 (
b0001110110010000 )
b0010110000110011 *
#327
0&
#328
b0000011011001101 #
b1101001111101111 $
b1110000101001001 %
1&
b0100100111000011 (
b0000011011001101 )
b1101001111101111 *
#329
0&
#330
b1101000100100001 #
b0001101111111110 $
b0010011110010011 %
1&
b1101101010111100 (
b1101000100100001 )
b0001101111111110 *
#331
0&
#332
b0000011100110000 #
b0011111000011011 $
b0010101110010011 %
1&
b1110110100011111 (
b0000011100110000 )
b0010101110010011 *
#333
0&
#334
b0001011101111111 #
b1101101100010010 $
b1101110000101000 %
1&
b0011001011000011 (
b0001011101111111 )
b1101101100010010 *
#335
0&
#336
b0001001010110010 #
b0010101001101101 $
b0010010010000001 %
1&
b1111001010010001 (
b0001001010110010 )
b0010010010000001 *
#337
0&
#338
b1110010101111001 #
b1100101001100100 $
b1101001110000101 %
1&
b0011011100110011 (
b1110010101111001 )
b1100101001100100 *
#339
0&
#340
b0011111100010010 #
b0000110110101111 $
b1101100100111011 %
1&
b1010111111011101 (
b0011111100010010 )
b1101100100111011 *
#341
0&
#342
b1110111011011111 #
b1101001010001010 $
b0010010011100111 %
1&
b0001100001001101 (
b1110111011011111 )
b1101001010001010 *
#343
0&
#344
b0011100001101101 #
b1101110101001110 $
b1111101110111001 %
1&
b1100000101101001 (
b0011100001101101 )
b1101110101001110 *
#345
0&
#346
b1111110011011000 #
b0001011000110011 $
b1100011010101010 %
1&
b0001010110111011 (
b1111110011011000 )
b1100011010101010 *
#347
0&
#348
b1100001000101011 #
b0000100000000111 $
b1101011101100001 %
1&
b1100001110000010 (
b1100001000101011 )
b1101011101100001 *
#349
0&
#350
b1110101010101110 #
b0011011000011100 $
b1100111010111010 %
1&
b1001100110001100 (
b1110101010101110 )
b1100111010111010 *
#351
0&
#352
b1111111111100111 #
b0001001000010100 $
b1100011110010001 %
1&
b1011100101101000 (
b1111111111100111 )
b1100011110010001 *
#353
0&
#354
b1100010110101001 #
b0010110100010000 $
b0011101110100101 %
1&
b1100011101111000 (
b1100010110101001 )
b0010110100010000 *
#355
0&
#356
b0001000100011011 #
b1111000111100100 $
b0010110111000101 %
1&
b1111001010111001 (
b0001000100011011 )
b1111000111100100 *
#357
0&
#358
b1100101101111111 #
b0011111110001101 $
b0000110000000110 %
1&
b0000001011111111 (
b1100101101111111 )
b0000110000000110 *
#359
0&
#360
b1100001100100011 #
b0000010001111101 $
b0010011000011011 %
1&
b1101011110000101 (
b1100001100100011 )
b0000010001111101 *
#361
0&
#362
b0001011111010011 #
b0001000111010101 $
b0001100110001001 %
1&
b1100011110100000 (
b0001011111010011 )
b0001000111010101 *
#363
0&
#364
b1110101000111110 #
b0000101111111100 $
b0010001001111000 %
1&
b0010100110101000 (
b1110101000111110 )
b0000101111111100 *
#365
0&
#366
b1110101001001000 #
b1111110000011011 $
b1100011000010011 %
1&
b1111011000111010 (
b1110101001001000 )
b1100011000010011 *
#367
0&
#368
b1110010101001011 #
b1110011001000000 $
b1100101111110101 %
1&
b1011000001011011 (
b1110010101001011 )
b1100101111110101 *
#369
0&
#370
b0000101100011010 #
b0011001001111110 $
b1110110100100110 %
1&
b1011000101000000 (
b0000101100011010 )
b1110110100100110 *
#371
0&
#372
b0010010111010110 #
b1111101010101110 $
b0001010101010001 %
1&
b1111100001000000 (
b0010010111010110 )
b1111101010101110 *
#373
0&
#374
b1100001101000011 #
b0011111101101100 $
b0001011011101101 %
1&
b0010000010000100 (
b1100001101000011 )
b0001011011101101 *
#375
0&
#376
b0000010000111000 #
b1101110001000100 $
b1101001111010101 %
1&
b1101101000110000 (
b0000010000111000 )
b1101001111010101 *
#377
0&
#378
b0001000100100010 #
b0001100000111011 $
b1100000010101011 %
1&
b1101100000001101 (
b0001000100100010 )
b1100000010101011 *
#379
0&
#380
b1111111100100001 #
b0010000111010011 $
b1111101110110000 %
1&
b1101000111001101 (
b1111111100100001 )
b1111101110110000 *
#381
0&
#382
b1101111110011000 #
b1100111110011010 $
b1100011010111010 %
1&
b1111101011010001 (
b1101111110011000 )
b1100011010111010 *
#383
0&
#384
b0011011111110101 #
b0010000001000010 $
b0001110010100111 %
1&
b1010011001010010 (
b0011011111110101 )
b0001110010100111 *
#385
0&
#386
b0000110010000011 #
b1100110101101100 $
b1100011110101100 %
1&
b0101010010011100 (
b0000110010000011 )
b1100011110101100 *
#387
0&
#388
b1110001100100011 #
b1110011011100011 $
b0000101100110001 %
1&
b1101010000101111 (
b1110001100100011 )
b1110011011100011 *
#389
0&
#390
b0010001110000001 #
b0011000101110111 $
b1101011011101111 %
1&
b1100101000000110 (
b0010001110000001 )
b1101011011101111 *
#391
0&
#392
b0011010101000110 #
b1100101101100110 $
b0000110101100010 %
1&
b1111101001110000 (
b0011010101000110 )
b1100101101100110 *
#393
0&
#394
b1111100101010011 #
b0010011011101001 $
b1100110001100100 %
1&
b0000000010101100 (
b1111100101010011 )
b1100110001100100 *
#395
0&
#396
b0000110001000001 #
b1110110000011111 $
b1110000111001010 %
1&
b1100010110110111 (
b0000110001000001 )
b1110000111001010 *
#397
0&
